actionfreeze/__init__.py
actionfreeze-0.0.1.dist-info/LICENSE
actionfreeze-0.0.1.dist-info/METADATA
actionfreeze-0.0.1.dist-info/WHEEL
actionfreeze-0.0.1.dist-info/top_level.txt
actionfreeze-0.0.1.dist-info/RECORD
