Metadata-Version: 2.1
Name: actionfreeze
Version: 0.0.1
Summary: Schedule a function to run repeatedly for a while.
Home-page: https://github.com/hirios/actionfreeze
Author: Alan Rios
Author-email: alanrioscosta@yahoo.com
License: UNKNOWN
Platform: UNKNOWN
Classifier: Programming Language :: Python :: 3
Classifier: License :: OSI Approved :: MIT License
Classifier: Operating System :: OS Independent
